django_gpg/__init__.py
django_gpg/admin.py
django_gpg/apps.py
django_gpg/fields.py
django_gpg/gpg.py
django_gpg/models.py
django_gpg/settings.py
django_gpg/tests.py
django_gpg/migrations/0001_initial.py
django_gpg/migrations/__init__.py
django_gpg-0.2.0.dist-info/DESCRIPTION.rst
django_gpg-0.2.0.dist-info/METADATA
django_gpg-0.2.0.dist-info/RECORD
django_gpg-0.2.0.dist-info/WHEEL
django_gpg-0.2.0.dist-info/metadata.json
django_gpg-0.2.0.dist-info/top_level.txt
