Metadata-Version: 2.0
Name: django-gpg
Version: 0.2.0
Summary: GPG Support for Django
Home-page: https://github.com/arecker/django-gpg
Author: Alex Recker
Author-email: alex@reckerfamily.com
License: GPLv3
Platform: UNKNOWN
Classifier: Environment :: Web Environment
Classifier: Framework :: Django
Classifier: Intended Audience :: Developers
Classifier: Operating System :: OS Independent
Classifier: Programming Language :: Python
Classifier: Topic :: Internet :: WWW/HTTP
Classifier: Topic :: Internet :: WWW/HTTP :: Dynamic Content
Requires-Dist: Django (==1.11.2)
Requires-Dist: gnupg (==2.3.0)
